[{"pk": 1, "model": "checkins.user", "fields": {"fb_id": 14, "twitter_id": 0, "lname": "Canberk", "fname": "Ilter", "email": "icanberk@me.com", "date_joined": "2012-09-02"}}, {"pk": 2, "model": "checkins.user", "fields": {"fb_id": 42, "twitter_id": 0, "lname": "Pandya", "fname": "Mihir", "email": "mp@andre.com", "date_joined": "2012-09-02"}}, {"pk": 1, "model": "checkins.checkin", "fields": {"latitude": "1.0000000", "comment": "\"hey\"", "u_id": 1, "when": "2012-09-02", "longitude": "10.0000000"}}, {"pk": 2, "model": "checkins.checkin", "fields": {"latitude": "15.0000000", "comment": "\"immahere\"", "u_id": 2, "when": "2012-09-02", "longitude": "10.0000000"}}, {"pk": 1, "model": "checkins.follow", "fields": {"following": 2, "follower": 1}}, {"pk": 2, "model": "checkins.follow", "fields": {"following": 2, "follower": 1}}]